{
  "IcoMoonType": "selection",
  "icons": [
    {
      "icon": {
        "paths": [
          "M658 707.333l-60 60-256-256 256-256 60 60-196 196z"
        ],
        "isMulticolor": false,
        "isMulticolor2": false,
        "tags": [
          "keyboard_arrow_left"
        ],
        "defaultCode": 58132,
        "grid": 0
      },
      "properties": {
        "id": 2,
        "order": 19,
        "ligatures": "",
        "prevSize": 32,
        "code": 58132,
        "name": "keyboard_arrow_left"
      },
      "setIdx": 0,
      "setId": 7,
      "iconIdx": 1
    },
    {
      "icon": {
        "paths": [
          "M366 719.333l196-196-196-196 60-60 256 256-256 256z"
        ],
        "isMulticolor": false,
        "isMulticolor2": false,
        "tags": [
          "keyboard_arrow_right"
        ],
        "defaultCode": 58133,
        "grid": 0
      },
      "properties": {
        "id": 3,
        "order": 18,
        "ligatures": "",
        "prevSize": 32,
        "code": 58133,
        "name": "keyboard_arrow_right"
      },
      "setIdx": 0,
      "setId": 7,
      "iconIdx": 2
    },
    {
      "icon": {
        "paths": [
          "M256 277.333h86v512h-86v-512zM786 729.333l-60 60-256-256 256-256 60 60-196 196z"
        ],
        "isMulticolor": false,
        "isMulticolor2": false,
        "tags": [
          "first_page"
        ],
        "defaultCode": 58844,
        "grid": 0
      },
      "properties": {
        "id": 8,
        "order": 17,
        "ligatures": "",
        "prevSize": 32,
        "code": 58844,
        "name": "first_page"
      },
      "setIdx": 0,
      "setId": 7,
      "iconIdx": 7
    },
    {
      "icon": {
        "paths": [
          "M682 277.333h86v512h-86v-512zM238 337.333l60-60 256 256-256 256-60-60 196-196z"
        ],
        "isMulticolor": false,
        "isMulticolor2": false,
        "tags": [
          "last_page"
        ],
        "defaultCode": 58845,
        "grid": 0
      },
      "properties": {
        "id": 9,
        "order": 16,
        "ligatures": "",
        "prevSize": 32,
        "code": 58845,
        "name": "last_page"
      },
      "setIdx": 0,
      "setId": 7,
      "iconIdx": 8
    },
    {
      "icon": {
        "paths": [
          "M512 938c-48 0-86-38-86-84h170c0 49.675-37.225 84-84 84zM768 470v212l86 86v42h-684v-42l86-86v-212c0-132 70-240 192-270v-30c0-36 28-64 64-64s64 28 64 64v30c122 30 192 140 192 270zM852 448c-6-114-64-212-150-274l60-60c102 78 170 198 176 334h-86zM324 174c-88 62-146 160-152 274h-86c6-136 74-256 176-334z"
        ],
        "attrs": [
          {}
        ],
        "isMulticolor": false,
        "isMulticolor2": false,
        "tags": [
          "notifications_active"
        ],
        "grid": 24
      },
      "attrs": [
        {}
      ],
      "properties": {
        "order": 1,
        "id": 4,
        "prevSize": 24,
        "code": 59657,
        "name": "notifications_active"
      },
      "setIdx": 2,
      "setId": 5,
      "iconIdx": 0
    },
    {
      "icon": {
        "paths": [
          "M316 658l-60-60 256-256 256 256-60 60-196-196z"
        ],
        "attrs": [
          {}
        ],
        "isMulticolor": false,
        "isMulticolor2": false,
        "tags": [
          "keyboard_arrow_up"
        ],
        "grid": 24
      },
      "attrs": [
        {}
      ],
      "properties": {
        "order": 1,
        "id": 3,
        "name": "keyboard_arrow_up",
        "prevSize": 24,
        "code": 59649
      },
      "setIdx": 2,
      "setId": 5,
      "iconIdx": 1
    },
    {
      "icon": {
        "paths": [
          "M316 334l196 196 196-196 60 60-256 256-256-256z"
        ],
        "attrs": [
          {}
        ],
        "isMulticolor": false,
        "isMulticolor2": false,
        "tags": [
          "keyboard_arrow_down"
        ],
        "grid": 24
      },
      "attrs": [
        {}
      ],
      "properties": {
        "order": 4,
        "id": 0,
        "name": "keyboard_arrow_down",
        "prevSize": 24,
        "code": 59652
      },
      "setIdx": 2,
      "setId": 5,
      "iconIdx": 4
    },
    {
      "icon": {
        "paths": [
          "M813.667 253q59 59 91.333 135.667 33.667 79.333 33.667 166t-33.667 166q-32.333 76.667-91.333 135.667t-135.667 91.333q-79.333 33.667-166 33.667t-166-33.667q-76.667-32.333-135.667-91.333t-91.333-135.667q-33.667-79.333-33.667-166t33.667-166q32.333-76.667 91.333-135.667 12.333-12.333 30-12.333t30.333 12.333 12.667 30-12.667 30.333q-47 47-73.333 108.333-26.667 64-26.667 133t26.667 133q26.333 61.333 73.333 108.333t108.333 73.333q64 26.667 133 26.667t133-26.667q61.333-26.333 108.333-73.333t73.333-108.333q26.667-64 26.667-133t-26.667-133q-26.333-61.333-73.333-108.333-12.667-12.667-12.667-30.333t12.667-30 30.333-12.333 30 12.333zM512 42.667q17.667 0 30.167 12.5t12.5 30.167v426.667q0 17.667-12.5 30.167t-30.167 12.5-30.167-12.5-12.5-30.167v-426.667q0-17.667 12.5-30.167t30.167-12.5z"
        ],
        "attrs": [
          {}
        ],
        "isMulticolor": false,
        "isMulticolor2": false,
        "tags": [
          "power"
        ],
        "grid": 24
      },
      "attrs": [
        {}
      ],
      "properties": {
        "order": 1,
        "id": 2,
        "prevSize": 24,
        "code": 59656,
        "name": "power"
      },
      "setIdx": 5,
      "setId": 2,
      "iconIdx": 0
    },
    {
      "icon": {
        "paths": [
          "M810.667 170.667q18.333 0 30.5 12.167t12.167 30.5q0 18-12.333 30.333l-268.667 268.333 268.667 268.333q12.333 12.333 12.333 30.333 0 18.333-12.167 30.5t-30.5 12.167q-18 0-30.333-12.333l-268.333-268.667-268.333 268.667q-12.333 12.333-30.333 12.333-18.333 0-30.5-12.167t-12.167-30.5q0-18 12.333-30.333l268.667-268.333-268.667-268.333q-12.333-12.333-12.333-30.333 0-18.333 12.167-30.5t30.5-12.167q18 0 30.333 12.333l268.333 268.667 268.333-268.667q12.333-12.333 30.333-12.333z"
        ],
        "attrs": [
          {}
        ],
        "isMulticolor": false,
        "isMulticolor2": false,
        "tags": [
          "cross"
        ],
        "grid": 24
      },
      "attrs": [
        {}
      ],
      "properties": {
        "order": 1,
        "id": 1,
        "prevSize": 24,
        "code": 59655,
        "name": "cross"
      },
      "setIdx": 5,
      "setId": 2,
      "iconIdx": 1
    },
    {
      "icon": {
        "paths": [
          "M128 213.333h768q17.667 0 30.167 12.5t12.5 30.167-12.5 30.167-30.167 12.5h-768q-17.667 0-30.167-12.5t-12.5-30.167 12.5-30.167 30.167-12.5zM128 725.333h768q17.667 0 30.167 12.5t12.5 30.167-12.5 30.167-30.167 12.5h-768q-17.667 0-30.167-12.5t-12.5-30.167 12.5-30.167 30.167-12.5zM128 469.333h768q17.667 0 30.167 12.5t12.5 30.167-12.5 30.167-30.167 12.5h-768q-17.667 0-30.167-12.5t-12.5-30.167 12.5-30.167 30.167-12.5z"
        ],
        "attrs": [
          {}
        ],
        "isMulticolor": false,
        "isMulticolor2": false,
        "tags": [
          "menu"
        ],
        "grid": 24
      },
      "attrs": [
        {}
      ],
      "properties": {
        "order": 1,
        "id": 0,
        "prevSize": 24,
        "code": 59648,
        "name": "menu"
      },
      "setIdx": 5,
      "setId": 2,
      "iconIdx": 2
    },
    {
      "icon": {
        "paths": [
          "M804.571 566.857v274.286c0 20-16.571 36.571-36.571 36.571h-219.429v-219.429h-146.286v219.429h-219.429c-20 0-36.571-16.571-36.571-36.571v-274.286c0-1.143 0.571-2.286 0.571-3.429l328.571-270.857 328.571 270.857c0.571 1.143 0.571 2.286 0.571 3.429zM932 527.429l-35.429 42.286c-2.857 3.429-7.429 5.714-12 6.286h-1.714c-4.571 0-8.571-1.143-12-4l-395.429-329.714-395.429 329.714c-4 2.857-8.571 4.571-13.714 4-4.571-0.571-9.143-2.857-12-6.286l-35.429-42.286c-6.286-7.429-5.143-19.429 2.286-25.714l410.857-342.286c24-20 62.857-20 86.857 0l139.429 116.571v-111.429c0-10.286 8-18.286 18.286-18.286h109.714c10.286 0 18.286 8 18.286 18.286v233.143l125.143 104c7.429 6.286 8.571 18.286 2.286 25.714z"
        ],
        "attrs": [
          {}
        ],
        "width": 951,
        "isMulticolor": false,
        "isMulticolor2": false,
        "tags": [
          "home"
        ],
        "grid": 14
      },
      "attrs": [
        {}
      ],
      "properties": {
        "order": 1,
        "id": 0,
        "name": "home",
        "prevSize": 28,
        "code": 59653
      },
      "setIdx": 3,
      "setId": 4,
      "iconIdx": 0
    },
    {
      "icon": {
        "paths": [
          "M528 928v0c-220.914 0-400-179.086-400-400s179.086-400 400-400c220.914 0 400 179.086 400 400s-179.086 400-400 400zM528 896c203.241 0 368-164.759 368-368s-164.759-368-368-368c-203.241 0-368 164.759-368 368s164.759 368 368 368v0zM627.889 350.947l-17.894 26.529 106.117 71.577 17.894-26.529-106.117-71.577zM321.995 422.524l17.894 26.529 106.117-71.577-17.894-26.529-106.117 71.577zM527.902 672c-95.902 0-143.902-32-143.902-32s32 96 144 96c112 0 144-96 144-96s-48.195 32-144.098 32v0z"
        ],
        "attrs": [
          {}
        ],
        "isMulticolor": false,
        "isMulticolor2": false,
        "tags": [
          "amused-face-closed-eyes"
        ],
        "grid": 32
      },
      "attrs": [
        {}
      ],
      "properties": {
        "order": 1,
        "id": 0,
        "name": "amused-face-closed-eyes",
        "prevSize": 32,
        "code": 59654
      },
      "setIdx": 4,
      "setId": 3,
      "iconIdx": 0
    },
    {
      "icon": {
        "paths": [
          "M384 640l128-64 448-448-64-64-448 448-64 128zM289.3 867.098c-31.632-66.728-65.666-100.762-132.396-132.394l99.096-272.792 128-77.912 384-384h-192l-384 384-192 640 640-192 384-384v-192l-384 384-77.912 128z"
        ],
        "tags": [
          "pencil",
          "write",
          "edit"
        ],
        "defaultCode": 59654,
        "grid": 16,
        "attrs": []
      },
      "attrs": [],
      "properties": {
        "ligatures": "pencil2, write2",
        "name": "pencil2",
        "order": 14,
        "id": 7,
        "prevSize": 32,
        "code": 59658
      },
      "setIdx": 6,
      "setId": 1,
      "iconIdx": 6
    },
    {
      "icon": {
        "width": 1152,
        "paths": [
          "M1088 128h-64v-64c0-35.2-28.8-64-64-64h-896c-35.2 0-64 28.8-64 64v768c0 35.2 28.8 64 64 64h64v64c0 35.2 28.8 64 64 64h896c35.2 0 64-28.8 64-64v-768c0-35.2-28.8-64-64-64zM128 192v640h-63.886c-0.040-0.034-0.082-0.076-0.114-0.116v-767.77c0.034-0.040 0.076-0.082 0.114-0.114h895.77c0.040 0.034 0.082 0.076 0.116 0.116v63.884h-768c-35.2 0-64 28.8-64 64v0zM1088 959.884c-0.034 0.040-0.076 0.082-0.116 0.116h-895.77c-0.040-0.034-0.082-0.076-0.114-0.116v-767.77c0.034-0.040 0.076-0.082 0.114-0.114h895.77c0.040 0.034 0.082 0.076 0.116 0.116v767.768z",
          "M960 352c0 53.020-42.98 96-96 96s-96-42.98-96-96 42.98-96 96-96 96 42.98 96 96z",
          "M1024 896h-768v-128l224-384 256 320h64l224-192z"
        ],
        "tags": [
          "images",
          "pictures",
          "photos",
          "graphics"
        ],
        "defaultCode": 59662,
        "grid": 16,
        "attrs": []
      },
      "attrs": [],
      "properties": {
        "ligatures": "images, pictures",
        "name": "images",
        "order": 9,
        "id": 15,
        "prevSize": 32,
        "code": 59662
      },
      "setIdx": 6,
      "setId": 1,
      "iconIdx": 14
    },
    {
      "icon": {
        "paths": [
          "M128 320v640c0 35.2 28.8 64 64 64h576c35.2 0 64-28.8 64-64v-640h-704zM320 896h-64v-448h64v448zM448 896h-64v-448h64v448zM576 896h-64v-448h64v448zM704 896h-64v-448h64v448z",
          "M848 128h-208v-80c0-26.4-21.6-48-48-48h-224c-26.4 0-48 21.6-48 48v80h-208c-26.4 0-48 21.6-48 48v80h832v-80c0-26.4-21.6-48-48-48zM576 128h-192v-63.198h192v63.198z"
        ],
        "tags": [
          "bin",
          "trashcan",
          "remove",
          "delete",
          "recycle",
          "dispose"
        ],
        "defaultCode": 59820,
        "grid": 16,
        "attrs": []
      },
      "attrs": [],
      "properties": {
        "ligatures": "bin, trashcan",
        "name": "bin",
        "order": 15,
        "id": 173,
        "prevSize": 32,
        "code": 59820
      },
      "setIdx": 6,
      "setId": 1,
      "iconIdx": 172
    }
  ],
  "height": 1024,
  "metadata": {
    "name": "icomoon"
  },
  "preferences": {
    "showGlyphs": true,
    "showQuickUse": true,
    "showQuickUse2": true,
    "showSVGs": true,
    "fontPref": {
      "prefix": "icon-",
      "metadata": {
        "fontFamily": "icomoon"
      },
      "metrics": {
        "emSize": 1024,
        "baseline": 6.25,
        "whitespace": 50
      },
      "embed": false
    },
    "imagePref": {
      "prefix": "icon-",
      "png": true,
      "useClassSelector": true,
      "color": 0,
      "bgColor": 16777215,
      "classSelector": ".icon"
    },
    "historySize": 50,
    "showCodes": true,
    "gridSize": 16
  }
}